README
setup.py
python3_digest.egg-info/PKG-INFO
python3_digest.egg-info/SOURCES.txt
python3_digest.egg-info/dependency_links.txt
python3_digest.egg-info/top_level.txt
python3_digest.egg-info/zip-safe
python_digest/__init__.py
python_digest/http.py
python_digest/tests.py
python_digest/utils.py